DigitalScale/__init__.py
MkNxGn_OpenScale-0.1.0.4.dist-info/LICENSE
MkNxGn_OpenScale-0.1.0.4.dist-info/METADATA
MkNxGn_OpenScale-0.1.0.4.dist-info/WHEEL
MkNxGn_OpenScale-0.1.0.4.dist-info/top_level.txt
MkNxGn_OpenScale-0.1.0.4.dist-info/RECORD
