Metadata-Version: 2.1
Name: MkNxGn-OpenScale
Version: 0.1.0.4
Summary: MkNxGn Sparkfun OpenScale Helper - Serial
Home-page: https://mknxgn.com/
Author: Mark Cartagena
Author-email: mark@mknxgn.com
License: UNKNOWN
Platform: UNKNOWN
Classifier: Programming Language :: Python :: 3
Classifier: License :: OSI Approved :: MIT License
Classifier: Operating System :: OS Independent
Requires-Dist: pyserial
